illumni/__init__.py
illumni/const.py
illumni/exc.py
illumni/net.py
illumni-1.0.2.dist-info/LICENSE
illumni-1.0.2.dist-info/METADATA
illumni-1.0.2.dist-info/WHEEL
illumni-1.0.2.dist-info/top_level.txt
illumni-1.0.2.dist-info/RECORD
